playerFramework/__init__.py
playerFramework/exceptions.py
playerFramework/paths.py
playerFramework-4.2.dist-info/METADATA
playerFramework-4.2.dist-info/WHEEL
playerFramework-4.2.dist-info/top_level.txt
playerFramework-4.2.dist-info/RECORD
